{
  "location": "",
  "name": "",
  "modules": [
    {
      "name": "bme280",
      "type": "bme280",
      "enabled": false,
      "offsets": {
        "temp": 0,
        "humidity": 0,
        "pressure": 0
      },
      "sampling": {
        "interval": "",
        "aggregation": "average"
      },
      "reporting": {
        "interval": ""
      },
      "destinations": [
        {
          "name": "mqtt",
          "topic": "data/weather/${state.location || 'unknown'}"
        },
        {
          "name": "mqtt",
          "topic": "cmnd/${module.hvacLocation || 'unknown'}/HVACRemoteTemp"
        },
        {
          "name": "influxdb",
          "measurement": "weather"
        }
      ],
      "additionalProperties": {
        "hvacLocation": "somewhere_specific"
      }
    },
    {
      "name": "ble-tracker",
      "type": "ble-tracker",
      "enabled": false,
      "devices": [{ "alias": "", "macAddress": "00:00:00:00:00:00" }],
      "sampling": {
        "interval": 10000,
        "aggregation": "average"
      },
      "mqttTopicPrefix": ""
    }
  ],
  "destinations": [
    {
      "name": "influxdb",
      "type": "influxdb",
      "enabled": false,
      "url": "",
      "organization": "",
      "bucket": "",
      "precision": "ms",
      "token": ""
    }
  ]
}
